Workbook
Name Financing: lists!$B$21:$B$23
Name Investing: lists!$B$17:$B$20
Name Operating: lists!$B$2:$B$16
Name Summary: lists!$B$24:$B$25

Sheet CashFlowStatement
A1: Start Date: | B1: 46023 | C1: CASH FLOW STATEMENT
A2: End Date: | B2: 46082
A3: Section | B3: Item | C3: Amount (₹)
A4: Operating Cash Flow
B5: Interest Income (Loan Repayments – Interest EMI): | C5: =SUMIFS(CashBook!$E:$E, CashBook!$C:$C, "Weekly EMI", CashBook!$A:$A, ">="&$B$1, CashBook!$A:$A, "<="&$B$2) +SUMIFS(CashBook!$E:$E, CashBook!$C:$C, "Daily EMI", CashBook!$A:$A, ">="&$B$1, CashBook!$A:$A, "<="&$B$2) -> 1700
B6: Interest Income (other lending): | C6: =SUMIFS(CashBook!$E:$E, CashBook!$D:$D, "Operating", CashBook!$C:$C, "Interest Income", CashBook!$A:$A, ">="&$B$1, CashBook!$A:$A, "<="&$B$2) -> 2200
B7: Processing Fees: | C7: =SUMIFS(CashBook!$E:$E, CashBook!$D:$D, "Operating", CashBook!$C:$C, "Processing Fee", CashBook!$A:$A, ">="&$B$1, CashBook!$A:$A, "<="&$B$2) -> 200
B8: Other Income: | C8: =SUMIFS(CashBook!$E:$E, CashBook!$D:$D, "Operating", CashBook!$C:$C, "Other Income", CashBook!$A:$A, ">="&$B$1, CashBook!$A:$A, "<="&$B$2) -> 3500
B9: Subtotal Inflows | C9: =SUM(C5:C8) -> 7600
B11: Interest Payment on Borrowings (Cost of Funds): | C11: =SUMIFS(CashBook!$F:$F, CashBook!$D:$D, "Operating", CashBook!$C:$C, "Interest Payment On Borrowings", CashBook!$A:$A, ">="&$B$1, CashBook!$A:$A, "<="&$B$2) -> 2700
B13: Operating Expenses:
B14: Salaries: | C14: =SUMIFS(CashBook!$F:$F, CashBook!$D:$D, "Operating", CashBook!$C:$C, "Salaries", CashBook!$A:$A, ">="&$B$1, CashBook!$A:$A, "<="&$B$2) -> 12000
B15: Rent: | C15: =SUMIFS(CashBook!$F:$F, CashBook!$D:$D, "Operating", CashBook!$C:$C, "Rent", CashBook!$A:$A, ">="&$B$1, CashBook!$A:$A, "<="&$B$2) -> 8000
B16: Utilities & Internet: | C16: =SUMIFS(CashBook!$F:$F, CashBook!$D:$D, "Operating", CashBook!$C:$C, "Utilities & Internet", CashBook!$A:$A, ">="&$B$1, CashBook!$A:$A, "<="&$B$2) -> 3500
B17: Office/Admin; | C17: =SUMIFS(CashBook!$F:$F, CashBook!$D:$D, "Operating", CashBook!$C:$C, "Office/Admin", CashBook!$A:$A, ">="&$B$1, CashBook!$A:$A, "<="&$B$2) -> 2000
B18: Misc. Expenses: | C18: =SUMIFS(CashBook!$F:$F, CashBook!$D:$D, "Operating", CashBook!$C:$C, "Misc. Expenses", CashBook!$A:$A, ">="&$B$1, CashBook!$A:$A, "<="&$B$2) -> 1500
B19: Subtotal Outflows | C19: =SUM(C11:C18) -> 29700
B20: Net Operating Cash | C20: =C9-C19 -> -22100
A22: Investing Cash Flow
B23: Asset Purchase (outflow): | C23: =SUMIFS(CashBook!$F:$F, CashBook!$D:$D, "Investing", CashBook!$C:$C, "Asset Purchase", CashBook!$A:$A, ">="&$B$1, CashBook!$A:$A, "<="&$B$2) -> 20000
B24: Sale of Asset (inflow): | C24: =SUMIFS(CashBook!$E:$E, CashBook!$D:$D, "Investing", CashBook!$C:$C, "Sale of Asset", CashBook!$A:$A, ">="&$B$1, CashBook!$A:$A, "<="&$B$2) -> 0
B25: Net Investing Cash | C25: =C23-C24 -> 20000
A27: Financing Cash Flow
B28: Borrowings (inflow): | C28: =SUMIFS(CashBook!$E:$E, CashBook!$D:$D, "Financing", CashBook!$C:$C, "Borrowing", CashBook!$A:$A, ">="&$B$1, CashBook!$A:$A, "<="&$B$2) -> 1000000
B29: Capital Injection (inflow): | C29: =SUMIFS(CashBook!$E:$E, CashBook!$D:$D, "Financing", CashBook!$C:$C, "Capital Injection", CashBook!$A:$A, ">="&$B$1, CashBook!$A:$A, "<="&$B$2) -> 500000
B30: Repayment (outflow): | C30: =SUMIFS(CashBook!$F:$F, CashBook!$D:$D, "Financing", CashBook!$C:$C, "Repayment", CashBook!$A:$A, ">="&$B$1, CashBook!$A:$A, "<="&$B$2) -> 15000
B31: Net Financing Cash | C31: =C28+C29-C30 -> 1485000
A33: Summary
B34: Opening Balance:
B35: Closing Balance:

Sheet IncomeStatement
A1: Start Date: | B1: 46023 | C1: INCOME STATEMENT
A2: End Date: | B2: 46082
A3: Section | B3: Item | C3: Amount (₹)
A4: Revenue
B5: Loan Repayments - Interest (EMI): | C5: =SUMIFS(CashBook!$E:$E, CashBook!$D:$D,"Operating", CashBook!$C:$C,"Weekly EMI", CashBook!$A:$A,">="&$B$1, CashBook!$A:$A,"<="&$B$2) +SUMIFS(CashBook!$E:$E, CashBook!$D:$D,"Operating", CashBook!$C:$C,"Daily EMI", CashBook!$A:$A,">="&$B$1, CashBook!$A:$A,"<="&$B$2) -> 1700
B6: Interest Income (other lending/credit lines): | C6: =SUMIFS(CashBook!$E:$E, CashBook!$D:$D,"Operating", CashBook!$C:$C,"Interest Income", CashBook!$A:$A,">="&$B$1, CashBook!$A:$A,"<="&$B$2) -> 2200
B7: Processing Fees: | C7: =SUMIFS(CashBook!$E:$E, CashBook!$D:$D, "Operating", CashBook!$C:$C, "Processing Fee", CashBook!$A:$A, ">="&$B$1, CashBook!$A:$A, "<="&$B$2) -> 200
B8: Other Income (if any): | C8: =SUMIFS(CashBook!$E:$E, CashBook!$D:$D, "Operating", CashBook!$C:$C, "Other Income", CashBook!$A:$A, ">="&$B$1, CashBook!$A:$A, "<="&$B$2) -> 3500
B9: Total Revenue: | C9: =SUM(C5:C8) -> 7600
A11: (Cost of Funds & Operating Costs)
B12: Interest Payment on Borrowings (Cost of Funds): | C12: =SUMIFS(CashBook!$F:$F, CashBook!$D:$D,"Operating", CashBook!$C:$C,"Interest Payment On Borrowings", CashBook!$A:$A,">="&$B$1, CashBook!$A:$A,"<="&$B$2) -> 2700
B14: Salaries: | C14: =SUMIFS(CashBook!$F:$F, CashBook!$D:$D, "Operating", CashBook!$C:$C, "Salaries", CashBook!$A:$A, ">="&$B$1, CashBook!$A:$A, "<="&$B$2) -> 12000
B15: Rent: | C15: =SUMIFS(CashBook!$F:$F, CashBook!$D:$D, "Operating", CashBook!$C:$C, "Rent", CashBook!$A:$A, ">="&$B$1, CashBook!$A:$A, "<="&$B$2) -> 8000
B16: Utilities & Internet: | C16: =SUMIFS(CashBook!$F:$F, CashBook!$D:$D, "Operating", CashBook!$C:$C, "Utilities & Internet", CashBook!$A:$A, ">="&$B$1, CashBook!$A:$A, "<="&$B$2) -> 3500
B17: Office/Admin: | C17: =SUMIFS(CashBook!$F:$F, CashBook!$D:$D, "Operating", CashBook!$C:$C, "Office/Admin", CashBook!$A:$A, ">="&$B$1, CashBook!$A:$A, "<="&$B$2) -> 2000
B18: Misc. Expenses: | C18: =SUMIFS(CashBook!$F:$F, CashBook!$D:$D, "Operating", CashBook!$C:$C, "Misc. Expenses", CashBook!$A:$A, ">="&$B$1, CashBook!$A:$A, "<="&$B$2) -> 1500
B19: Operating Expenses: | C19: =SUM(C14:C18) -> 27000
B20: Loan Loss Provision: | C20: 0
B21: Total Expenses: | C21: =C12+C19+C20 -> 29700
A23: Summary
B24: Net Interest Income (NII): | C24: =(C5+C6)-C12 -> 1200
B25: Operating Profit Before Provision: | C25: =C9-(C12+C19) -> -22100
B26: EBITDA: | C26: =C25-C20 -> -22100
B27: Depreciation: | C27: =C30-C22 -> 0
B28: Amortization:
B29: EBIT (Operating Profit): | C29: =C26-C27-C28 -> -22100
B30: Income Tax:
B31: Net Profit (Loss): | C31: =C29-C30 -> -22100
B34: Note:
B35: Net Interest Income (NII)
B36: ( 𝐿 𝑜 𝑎 𝑛 𝑅 𝑒 𝑝 𝑎 𝑦 𝑚 𝑒 𝑛 𝑡 𝑠 – 𝐼 𝑛 𝑡 𝑒 𝑟 𝑒 𝑠 𝑡 + 𝐼 𝑛 𝑡 𝑒 𝑟 𝑒 𝑠 𝑡 𝐼 𝑛 𝑐 𝑜 𝑚 𝑒 ) − ( 𝐼 𝑛 𝑡 𝑒 𝑟 𝑒 𝑠 𝑡 𝑃 𝑎 𝑦 𝑚 𝑒 𝑛 𝑡 𝑜 𝑛 𝐵 𝑜 𝑟 𝑟 𝑜 𝑤 𝑖 𝑛 𝑔 𝑠 ) = ( 231.66 + 200 ) − 300 = 131.66
B38: Operating Profit Before Provision
B39: 𝑁 𝐼 𝐼 + 𝐹 𝑒 𝑒 𝑠 + 𝑂 𝑡 ℎ 𝑒 𝑟 𝐼 𝑛 𝑐 𝑜 𝑚 𝑒 − 𝑂 𝑝 𝑒 𝑟 𝑎 𝑡 𝑖 𝑛 𝑔 𝐸 𝑥 𝑝 𝑒 𝑛 𝑠 𝑒 𝑠 = 131.66 + 200 + 300 − ( 100 + 100 + 20 + 20 + 5 ) = 386.66
B41: Profit Before Tax (PBT)
B42: =386.66 − 𝐿 𝑜 𝑎 𝑛 𝐿 𝑜 𝑠 𝑠 𝑃 𝑟 𝑜 𝑣 𝑖 𝑠 𝑖 𝑜 𝑛

Sheet BalanceSheet
C1: Start Date: | D1: 46082
C2: End Date: | D2: 46112
C3: BALANCE SHEET
A4: Assets | D4: (in ₹)
B5: Cash & Bank Balances
C6: Opening Balance: | D6: =CashFlowStatement!C34 -> 0
C7: Closing Balance: | D7: =CashFlowStatement!C35 -> 0
B9: Loans & Advances (Net of Principal Repayments)
C10: Loan Principal Outstanding: | D10: =[1]Portfolio!$K$2 -> 332091.93
C11: Izra Advances: | D11: 120
B12: Investments
C13: Prior Assets: | D13: =SUMIFS(CashBook!$F:$F, CashBook!$D:$D,"Investing", CashBook!$C:$C,"Asset Purchase", CashBook!$A:$A,"<"&$D$1) - SUMIFS(CashBook!$E:$E, CashBook!$D:$D,"Investing", CashBook!$C:$C,"Sale of Asset", CashBook!$A:$A,"<"&$D$1) -> 20000
C14: Asset Purchase (for the Month): | D14: =SUMIFS(CashBook!$F:$F, CashBook!$D:$D,"Investing", CashBook!$C:$C,"Asset Purchase", CashBook!$A:$A,">="&$D$1, CashBook!$A:$A,"<="&$D$2) -> 0
C15: Sale of Asset: | D15: =SUMIFS(CashBook!$E:$E, CashBook!$D:$D,"Investing", CashBook!$C:$C,"Sale of Asset", CashBook!$A:$A,">="&$D$1, CashBook!$A:$A,"<="&$D$2) -> 0
C16: Net Investments:
C17: Total Assets | D17: =D7+D10+D11+D13+D14+D15+D16 -> 352211.93
A19: Liabilities
B20: Borrowings
C21: Prior Borrowings: | D21: =SUMIFS(CashBook!$E:$E, CashBook!$D:$D,"Financing", CashBook!$C:$C,"Borrowing", CashBook!$A:$A,"<"&$D$1) - SUMIFS(CashBook!$F:$F, CashBook!$D:$D,"Financing", CashBook!$C:$C,"Repayment", CashBook!$A:$A,"<"&$D$1) -> 985000
C22: New Borrowings (for the Month): | D22: =SUMIFS( CashBook!$B:$B, CashBook!$D:$D,"Financing", CashBook!$C:$C,"Borrowing", CashBook!$A:$A,">="&$D$1, CashBook!$A:$A,"<="&$D$2 ) -> 0
C23: Repayments: | D23: =SUMIFS( CashBook!$F:$F, CashBook!$D:$D,"Financing", CashBook!$C:$C,"Repayment", CashBook!$A:$A,">="&$D$1, CashBook!$A:$A,"<="&$D$2 ) -> 0
C24: Net Borrowings Outstanding | D24: =D21+D22-D23 -> 985000
B26: Deposits / Capital Injection
C27: Prior Capital Injection: | D27: =SUMIFS( CashBook!$E:$E, CashBook!$D:$D,"Financing", CashBook!$C:$C,"Capital Injection", CashBook!$A:$A,"<"&$D$1 ) -> 500000
C28: Prior Capital Injection (for the Month): | D28: =SUMIFS( CashBook!$E:$E, CashBook!$D:$D,"Financing", CashBook!$C:$C,"Capital Injection", CashBook!$A:$A,">="&$D$1, CashBook!$A:$A,"<="&$D$2 ) -> 0
C29: Total Deposits: | D29: =D27+D28 -> 500000
B31: Other Liabilities
C32: Accrued Interest Payable:
C33: Operating Payables (salaries, rent, utilities if unpaid).
C34: Total Other Liabilities: | D34: =D32+D33 -> 0
C36: Total Liabilities: | D36: =D24+D29+D34 -> 1485000
A38: Equity
C39: Capital: | D39: =D29 -> 500000
C40: Reserves & Surplus: Retained earnings: | D40: =IncomeStatement!C31 -> -22100
C43: Total Equity: | D43: =D39+D40 -> 477900

Sheet lists
A1: Category | B1: Sub‑Category | C1: Purpose / Linkage
A2: Operating | B2: Daily EMI | C2: Cash inflow from scheduled loan repayments (principal + interest).
A3: Operating | B3: Weekly EMI | C3: Same as above, but for daily repayment loans.
A4: Operating | B4: Daily Loan | C4: Pure interest inflows (credit lines, overdrafts, non‑EMI loans).
A5: Operating | B5: Weekly Loan | C5: Same as above, but for daily repayment loans.
A6: Operating | B6: Interest Income | C6: Pure interest inflows (credit lines, overdrafts, non‑EMI loans).
A7: Operating | B7: Interest Payment On Borrowings
A8: Operating | B8: Processing Fee | C8: Fee income from loan disbursements (1% or CashBook tagged “Processing Fee”).
A9: Operating | B9: Other Income | C9: Any miscellaneous operating inflows (e.g., penalties, service charges).
A10: Operating | B10: Expense | C10: Operating outflows (utilities, admin, salaries, rent, etc. if tracked in CashBook).
A11: Operating | B11: Salaries
A12: Operating | B12: Rent
A13: Operating | B13: Utilities & Internet
A14: Operating | B14: Office/Admin
A15: Operating | B15: Misc. Expenses
A16: Operating | B16: Expense
A17: Investing | B17: Izra Advance | C17: Rs 60000 paid to farmer for annual grain repayment
A18: Investing | B18: Grain Repayment (annual)
A19: Investing | B19: Asset Purchase | C19: Outflow for buying fixed assets.
A20: Investing | B20: Sale of Asset | C20: Inflow from selling fixed assets.
A21: Financing | B21: Borrowing | C21: Inflow from new borrowings (loan capital received).
A22: Financing | B22: Capital Injection | C22: Inflow from equity/funds injected by promoters.
A23: Financing | B23: Repayment | C23: Outflow for financing repayments (your own borrowings being repaid).
A24: Summary | B24: Opening Balance | C24: Starting cash balance for the reporting window.
A25: Summary | B25: Closing Balance | C25: Ending cash balance for the reporting window.

Sheet CashBook
A1: PaymentDate | B1: Reference Id | C1: Transaction Description | D1: Category | E1: Debit (CashIn) | F1: Credit (CashOut) | G1: Balance
A3: 46023 | B3: Cap-01Jan26-01 | C3: Capital Injection | D3: Financing | E3: 500000 | G3: 25000
A4: 46027 | B4: Bor-05Jan26-01 | C4: Borrowing | D4: Financing | E4: 1000000 | G4: 65000
A5: 46031 | B5: Rep-10Jan26-01 | C5: Daily EMI | D5: Operating | F5: 10000 | G5: 50000
A6: 46032 | B6: Ass-15Jan26-01 | C6: Weekly EMI | D6: Operating | F6: 20000 | G6: 30000
A7: 46032 | B7: Rep-10Jan26-01 | C7: Repayment | D7: Financing | F7: 15000 | G7: 50000
A8: 46037 | B8: Ass-15Jan26-01 | C8: Asset Purchase | D8: Investing | F8: 20000 | G8: 30000
A9: 46042 | B9: Sal-20Jan26-01 | C9: Salaries | D9: Operating | F9: 12000 | G9: 18000
A10: 46047 | B10: Ren-25Jan26-01 | C10: Rent | D10: Operating | F10: 8000 | G10: 10000
A11: 46052 | B11: Uti-30Jan26-01 | C11: Utilities & Internet | D11: Operating | F11: 3500 | G11: 6500
A12: 46058 | B12: Off-05Feb26-01 | C12: Office/Admin | D12: Operating | F12: 2000 | G12: 4500
A13: 46063 | B13: Mis-10Feb26-01 | C13: Misc. Expenses | D13: Operating | F13: 1500 | G13: 3000
A14: 46068 | B14: Int-15Feb26-01 | C14: Interest Income | D14: Operating | E14: 2200 | G14: 5200
A15: 46073 | B15: Pro-20Feb26-01 | C15: Processing Fee | D15: Operating | E15: 200 | G15: 5400
A16: 46078 | B16: Oth-25Feb26-01 | C16: Other Income | D16: Operating | E16: 3500 | G16: 8900
A17: 46082 | B17: IPB-01Mar26-01 | C17: Interest Payment On Borrowings | D17: Operating | F17: 2700 | G17: 6200
A18: 46082 | B18: EMI-01Mar26-01 | C18: Daily EMI | D18: Operating | E18: 700 | G18: 5500
A19: 46082 | B19: EMI-01Mar26-02 | C19: Weekly EMI | D19: Operating | E19: 1000 | G19: 4500
A20: 46113 | B20: Izr-01Apr26-01 | C20: Izra Advance | D20: Investing | F20: 120000 | G20: 4220
A21: 46357 | B21: Grn-01Dec26-01 | C21: Grain Repayment (annual) | D21: Investing | E21: 42000
A22: 46387 | B22: Cls-31Dec26-01 | C22: Closing Balance | D22: Summary | G22: 264000
